aardvark_hwp/__init__.py
aardvark_hwp/main.py
aardvark_hwp/server.py
aardvark_hwp/xml_utils.py
aardvark_hwp-0.1.1.dist-info/METADATA
aardvark_hwp-0.1.1.dist-info/WHEEL
aardvark_hwp-0.1.1.dist-info/entry_points.txt
aardvark_hwp-0.1.1.dist-info/licenses/LICENSE
aardvark_hwp-0.1.1.dist-info/RECORD
