Metadata-Version: 2.4
Name: aardvark-hwp
Version: 0.1.1
Summary: PDF와 HWP 파일 간 변환을 지원하는 MCP 서버
Project-URL: Repository, https://github.com/your-username/aardvark-hwp
Project-URL: Issues, https://github.com/your-username/aardvark-hwp/issues
Author-email: Sang <sang4@example.com>
License: MIT
License-File: LICENSE
Keywords: conversion,document,hwp,korean,mcp,pdf
Classifier: Development Status :: 3 - Alpha
Classifier: Intended Audience :: Developers
Classifier: License :: OSI Approved :: MIT License
Classifier: Programming Language :: Python :: 3
Classifier: Programming Language :: Python :: 3.10
Classifier: Programming Language :: Python :: 3.11
Classifier: Programming Language :: Python :: 3.12
Classifier: Topic :: Office/Business
Classifier: Topic :: Text Processing :: General
Requires-Python: >=3.10
Requires-Dist: fastmcp>=0.2.0
Requires-Dist: httpx>=0.27.0
Requires-Dist: lxml>=4.9.0
Requires-Dist: mcp>=1.0.0
